pipCase/__init__.py
pipCase/test.py
pipCase-1.0.0.1.dist-info/LICENSE
pipCase-1.0.0.1.dist-info/METADATA
pipCase-1.0.0.1.dist-info/WHEEL
pipCase-1.0.0.1.dist-info/top_level.txt
pipCase-1.0.0.1.dist-info/RECORD
