Metadata-Version: 2.1
Name: pipCase
Version: 1.0.0.1
Summary: 这是一个pip上传自定义包的测试包
Home-page: UNKNOWN
Author: 许焕燃
Author-email: 527077832@qq.com
License: UNKNOWN
Platform: UNKNOWN
Requires-Python: >=3
License-File: LICENSE
Requires-Dist: pillow
